{"nodes": [{"id": "g_infogastos_infogastos_app_viaticos_app_viaticos_vite_config_js", "label": "vite.config.js", "file_type": "code", "source_file": "G:\\InfoGastos\\Infogastos\\App viaticos\\APP-VIATICOS-\\vite.config.js", "source_location": "L1"}], "edges": [{"source": "g_infogastos_infogastos_app_viaticos_app_viaticos_vite_config_js", "target": "vite", "relation": "imports_from", "context": "import", "confidence": "EXTRACTED", "source_file": "G:\\InfoGastos\\Infogastos\\App viaticos\\APP-VIATICOS-\\vite.config.js", "source_location": "L1", "weight": 1.0}, {"source": "g_infogastos_infogastos_app_viaticos_app_viaticos_vite_config_js", "target": "plugin_vue", "relation": "imports_from", "context": "import", "confidence": "EXTRACTED", "source_file": "G:\\InfoGastos\\Infogastos\\App viaticos\\APP-VIATICOS-\\vite.config.js", "source_location": "L2", "weight": 1.0}], "raw_calls": []}